survivor_optimizer/__init__.py
survivor_optimizer/survivor_optimizer.py
survivor_optimizer-0.1.dist-info/LICENSE.txt
survivor_optimizer-0.1.dist-info/METADATA
survivor_optimizer-0.1.dist-info/WHEEL
survivor_optimizer-0.1.dist-info/top_level.txt
survivor_optimizer-0.1.dist-info/RECORD
