Metadata-Version: 2.1
Name: survivor_optimizer
Version: 0.1
Summary: Survivor optimizer: A competitive strategy for enhanced search efficiency
Home-page: https://www.sciencedirect.com/science/article/pii/S2090447925003028
Author: َArif Yelği
Author-email: ar.yelqi@gmail.com
Maintainer: Shirmohammad Tavangari
Maintainer-email: shmt.researcher@gmail.com
Requires-Python: >=3.7
License-File: LICENSE.txt
Requires-Dist: numpy
